[
  {
    "evidence_id": "ev-70b591e5",
    "category": "sex",
    "value": "Female",
    "source_file": "patient 2 (1).pdf",
    "page_number": 1,
    "excerpt": "Female",
    "status": "verified",
    "confidence": 1.0,
    "readable": true,
    "identity_compatible": true,
    "conflict_ids": []
  },
  {
    "evidence_id": "ev-3cf14190",
    "category": "principal_diagnosis",
    "value": "Acute Gastroenteritis with Dehydration",
    "source_file": "patient 2 (1).pdf",
    "page_number": 1,
    "excerpt": "ACUTE GASTROENTERITIS WITH DEHYDRATION",
    "status": "conflicting",
    "confidence": 1.0,
    "readable": true,
    "identity_compatible": true,
    "conflict_ids": [
      "conflict-73bf9888"
    ]
  },
  {
    "evidence_id": "ev-689ed80d",
    "category": "secondary_diagnosis",
    "value": "Urinary Tract Infection",
    "source_file": "patient 2 (1).pdf",
    "page_number": 1,
    "excerpt": "URINARY TRACT INFECTION",
    "status": "verified",
    "confidence": 1.0,
    "readable": true,
    "identity_compatible": true,
    "conflict_ids": []
  },
  {
    "evidence_id": "ev-7f951917",
    "category": "clinical_context",
    "value": "Multiple episodes of loose stools, 2-3 episodes of vomiting, fatigue since 3 days and fever since yesterday.",
    "source_file": "patient 2 (1).pdf",
    "page_number": 1,
    "excerpt": "Multiple episodes of loose stools, 2-3 episodes of vomiting, fatigue since 3 days and fever since yesterday.",
    "status": "verified",
    "confidence": 1.0,
    "readable": true,
    "identity_compatible": true,
    "conflict_ids": []
  },
  {
    "evidence_id": "ev-708a19b4",
    "category": "clinical_context",
    "value": "Initially she was treated at local clinic.",
    "source_file": "patient 2 (1).pdf",
    "page_number": 1,
    "excerpt": "Initially she was treated at local clinic.",
    "status": "verified",
    "confidence": 1.0,
    "readable": true,
    "identity_compatible": true,
    "conflict_ids": []
  },
  {
    "evidence_id": "ev-e194b59e",
    "category": "clinical_context",
    "value": "Thyroid disorder on treatment.",
    "source_file": "patient 2 (1).pdf",
    "page_number": 1,
    "excerpt": "Thyroid disorder on treatment.",
    "status": "verified",
    "confidence": 1.0,
    "readable": true,
    "identity_compatible": true,
    "conflict_ids": []
  },
  {
    "evidence_id": "ev-12fbcf14",
    "category": "clinical_context",
    "value": "PR-89/min",
    "source_file": "patient 2 (1).pdf",
    "page_number": 1,
    "excerpt": "PR-89/min",
    "status": "verified",
    "confidence": 1.0,
    "readable": true,
    "identity_compatible": true,
    "conflict_ids": []
  },
  {
    "evidence_id": "ev-c0ae783c",
    "category": "clinical_context",
    "value": "BP-130/80 mmHg",
    "source_file": "patient 2 (1).pdf",
    "page_number": 1,
    "excerpt": "BP-130/80 mmHg",
    "status": "verified",
    "confidence": 1.0,
    "readable": true,
    "identity_compatible": true,
    "conflict_ids": []
  },
  {
    "evidence_id": "ev-ff7e154f",
    "category": "clinical_context",
    "value": "RR-20/min",
    "source_file": "patient 2 (1).pdf",
    "page_number": 1,
    "excerpt": "RR-20/min",
    "status": "verified",
    "confidence": 1.0,
    "readable": true,
    "identity_compatible": true,
    "conflict_ids": []
  },
  {
    "evidence_id": "ev-94b5ad0b",
    "category": "clinical_context",
    "value": "SPO2-98% at room air.",
    "source_file": "patient 2 (1).pdf",
    "page_number": 1,
    "excerpt": "SPO2-98% at room air.",
    "status": "verified",
    "confidence": 1.0,
    "readable": true,
    "identity_compatible": true,
    "conflict_ids": []
  },
  {
    "evidence_id": "ev-3cfa4282",
    "category": "clinical_context",
    "value": "CNS-Conscious Oriented",
    "source_file": "patient 2 (1).pdf",
    "page_number": 1,
    "excerpt": "CNS-Conscious Oriented",
    "status": "verified",
    "confidence": 1.0,
    "readable": true,
    "identity_compatible": true,
    "conflict_ids": []
  },
  {
    "evidence_id": "ev-e58d3eea",
    "category": "clinical_context",
    "value": "CVS-S1S2(+)",
    "source_file": "patient 2 (1).pdf",
    "page_number": 1,
    "excerpt": "CVS-S1S2(+)",
    "status": "verified",
    "confidence": 1.0,
    "readable": true,
    "identity_compatible": true,
    "conflict_ids": []
  },
  {
    "evidence_id": "ev-d17c4168",
    "category": "clinical_context",
    "value": "RS-B/L NVBS(+)",
    "source_file": "patient 2 (1).pdf",
    "page_number": 1,
    "excerpt": "RS-B/L NVBS(+)",
    "status": "verified",
    "confidence": 1.0,
    "readable": true,
    "identity_compatible": true,
    "conflict_ids": []
  },
  {
    "evidence_id": "ev-d54114c2",
    "category": "clinical_context",
    "value": "PA-Soft, non tender",
    "source_file": "patient 2 (1).pdf",
    "page_number": 1,
    "excerpt": "PA-Soft, non tender",
    "status": "verified",
    "confidence": 1.0,
    "readable": true,
    "identity_compatible": true,
    "conflict_ids": []
  },
  {
    "evidence_id": "ev-c4ed1fbb",
    "category": "clinical_context",
    "value": "Reports Enclosed",
    "source_file": "patient 2 (1).pdf",
    "page_number": 1,
    "excerpt": "Reports Enclosed",
    "status": "verified",
    "confidence": 1.0,
    "readable": true,
    "identity_compatible": true,
    "conflict_ids": []
  },
  {
    "evidence_id": "ev-8a8e0b1e",
    "category": "hospital_course",
    "value": "Patient presented to us with above mentioned complaints. After evaluation, she was admitted to ward.",
    "source_file": "patient 2 (1).pdf",
    "page_number": 1,
    "excerpt": "Patient presented to us with above mentioned complaints. After evaluation, she was admitted to ward.",
    "status": "verified",
    "confidence": 1.0,
    "readable": true,
    "identity_compatible": true,
    "conflict_ids": []
  },
  {
    "evidence_id": "ev-de301e05",
    "category": "hospital_course",
    "value": "Initial investigations showed normal CBC.",
    "source_file": "patient 2 (1).pdf",
    "page_number": 1,
    "excerpt": "Initial investigations showed normal CBC.",
    "status": "verified",
    "confidence": 1.0,
    "readable": true,
    "identity_compatible": true,
    "conflict_ids": []
  },
  {
    "evidence_id": "ev-38d1152e",
    "category": "hospital_course",
    "value": "Serum creatinine (1.65mg/dl) done was elevated.",
    "source_file": "patient 2 (1).pdf",
    "page_number": 1,
    "excerpt": "Serum creatinine (1.65mg/dl) done was elevated.",
    "status": "verified",
    "confidence": 1.0,
    "readable": true,
    "identity_compatible": true,
    "conflict_ids": []
  },
  {
    "evidence_id": "ev-b5490937",
    "category": "hospital_course",
    "value": "Serum electrolytes done showed low serum sodium(128.00mmol/L).",
    "source_file": "patient 2 (1).pdf",
    "page_number": 1,
    "excerpt": "Serum electrolytes done showed low serum sodium(128.00mmol/L).",
    "status": "verified",
    "confidence": 1.0,
    "readable": true,
    "identity_compatible": true,
    "conflict_ids": []
  },
  {
    "evidence_id": "ev-9495bbd9",
    "category": "hospital_course",
    "value": "Urine routine done showed ketone bodies(+), 10-12/hpf of pus cells, 15-20/hpf of epithelial cells with presence of bactreia",
    "source_file": "patient 2 (1).pdf",
    "page_number": 1,
    "excerpt": "Urine routine done showed ketone bodies(+), 10-12/hpf of pus cells, 15-20/hpf of epithelial cells with presence of bactreia",
    "status": "verified",
    "confidence": 1.0,
    "readable": true,
    "identity_compatible": true,
    "conflict_ids": []
  },
  {
    "evidence_id": "ev-e1efea46",
    "category": "pending_result",
    "value": "urine culture and sensitivity sent- report awaited.",
    "source_file": "patient 2 (1).pdf",
    "page_number": 1,
    "excerpt": "urine culture and sensitivity sent- report awaited.",
    "status": "verified",
    "confidence": 1.0,
    "readable": true,
    "identity_compatible": true,
    "conflict_ids": []
  },
  {
    "evidence_id": "ev-0aab6d5e",
    "category": "medication",
    "value": "IV fluids",
    "source_file": "patient 2 (1).pdf",
    "page_number": 1,
    "excerpt": "She was treated with IV fluids,",
    "status": "verified",
    "confidence": 1.0,
    "readable": true,
    "identity_compatible": true,
    "conflict_ids": []
  },
  {
    "evidence_id": "ev-cc401315",
    "category": "hospital_course",
    "value": "IV antibiotics, IV PPI's, IV antiemetics and other supportive measures.",
    "source_file": "patient 2 (1).pdf",
    "page_number": 2,
    "excerpt": "IV antibiotics, IV PPI's, IV antiemetics and other supportive measures.",
    "status": "verified",
    "confidence": 1.0,
    "readable": true,
    "identity_compatible": true,
    "conflict_ids": []
  },
  {
    "evidence_id": "ev-ea7f3b66",
    "category": "clinical_context",
    "value": "USG abdomen and pelvis done showed Grade-I fatty liver changes",
    "source_file": "patient 2 (1).pdf",
    "page_number": 2,
    "excerpt": "USG abdomen and pelvis done showed Grade-I fatty liver changes",
    "status": "verified",
    "confidence": 1.0,
    "readable": true,
    "identity_compatible": true,
    "conflict_ids": []
  },
  {
    "evidence_id": "ev-b9ab8217",
    "category": "principal_diagnosis",
    "value": "Grade-I fatty liver changes",
    "source_file": "patient 2 (1).pdf",
    "page_number": 2,
    "excerpt": "Grade-I fatty liver changes",
    "status": "conflicting",
    "confidence": 1.0,
    "readable": true,
    "identity_compatible": true,
    "conflict_ids": [
      "conflict-73bf9888"
    ]
  },
  {
    "evidence_id": "ev-4118cecd",
    "category": "clinical_context",
    "value": "mildly edematous part of ascending colon upto the hepatic flexure- could represent colitis.",
    "source_file": "patient 2 (1).pdf",
    "page_number": 2,
    "excerpt": "mildly edematous part of ascending colon upto the hepatic flexure- could represent colitis.",
    "status": "verified",
    "confidence": 1.0,
    "readable": true,
    "identity_compatible": true,
    "conflict_ids": []
  },
  {
    "evidence_id": "ev-12e0bebc",
    "category": "secondary_diagnosis",
    "value": "colitis",
    "source_file": "patient 2 (1).pdf",
    "page_number": 2,
    "excerpt": "could represent colitis.",
    "status": "verified",
    "confidence": 1.0,
    "readable": true,
    "identity_compatible": true,
    "conflict_ids": []
  },
  {
    "evidence_id": "ev-4856855c",
    "category": "hospital_course",
    "value": "Repeat Serum Creatinine(1.17mg/dl) done was normal.",
    "source_file": "patient 2 (1).pdf",
    "page_number": 2,
    "excerpt": "Repeat Serum Creatinine(1.17mg/dl) done was normal.",
    "status": "verified",
    "confidence": 1.0,
    "readable": true,
    "identity_compatible": true,
    "conflict_ids": []
  },
  {
    "evidence_id": "ev-a6231a73",
    "category": "hospital_course",
    "value": "TSH and Free T4 done were normal.",
    "source_file": "patient 2 (1).pdf",
    "page_number": 2,
    "excerpt": "TSH and Free T4 done were normal.",
    "status": "verified",
    "confidence": 1.0,
    "readable": true,
    "identity_compatible": true,
    "conflict_ids": []
  },
  {
    "evidence_id": "ev-fce868e7",
    "category": "hospital_course",
    "value": "Stool routine done showed 2-3/hpf of red blood cells, plenty/hpf of pus cells.",
    "source_file": "patient 2 (1).pdf",
    "page_number": 2,
    "excerpt": "Stool routine done showed 2-3/hpf of red blood cells, plenty/hpf of pus cells.",
    "status": "verified",
    "confidence": 1.0,
    "readable": true,
    "identity_compatible": true,
    "conflict_ids": []
  },
  {
    "evidence_id": "ev-b1e07292",
    "category": "hospital_course",
    "value": "Patient was advised to stay back for further management but attenders not willing to the same, hence being discharged at request with following advice.",
    "source_file": "patient 2 (1).pdf",
    "page_number": 2,
    "excerpt": "Patient was advised to stay back for further management but attenders not willing to the same, hence being discharged at request with following advice.",
    "status": "verified",
    "confidence": 1.0,
    "readable": true,
    "identity_compatible": true,
    "conflict_ids": []
  },
  {
    "evidence_id": "ev-62dc8ae6",
    "category": "discharge_condition",
    "value": "Hemodynamically stable",
    "source_file": "patient 2 (1).pdf",
    "page_number": 2,
    "excerpt": "Hemodynamically stable",
    "status": "verified",
    "confidence": 1.0,
    "readable": true,
    "identity_compatible": true,
    "conflict_ids": []
  },
  {
    "evidence_id": "ev-af4bdd92",
    "category": "pending_result",
    "value": "Urine culture and sensitivity sent- report awaited.",
    "source_file": "patient 2 (1).pdf",
    "page_number": 2,
    "excerpt": "Urine culture and sensitivity sent- report awaited.",
    "status": "verified",
    "confidence": 1.0,
    "readable": true,
    "identity_compatible": true,
    "conflict_ids": []
  },
  {
    "evidence_id": "ev-25472eae",
    "category": "follow_up",
    "value": "Review immediately in case of fever, loose stools, vomiting, fatigue.",
    "source_file": "patient 2 (1).pdf",
    "page_number": 2,
    "excerpt": "Review immediately in case of fever, loose stools, vomiting, fatigue.",
    "status": "verified",
    "confidence": 1.0,
    "readable": true,
    "identity_compatible": true,
    "conflict_ids": []
  },
  {
    "evidence_id": "ev-92244319",
    "category": "follow_up",
    "value": "Review on 09.03.2026. CBC",
    "source_file": "patient 2 (1).pdf",
    "page_number": 2,
    "excerpt": "Review on 09.03.2026. CBC",
    "status": "verified",
    "confidence": 1.0,
    "readable": true,
    "identity_compatible": true,
    "conflict_ids": []
  },
  {
    "evidence_id": "ev-c6cb0dc6",
    "category": "medication",
    "value": "TAB. RACIPER",
    "source_file": "patient 2 (1).pdf",
    "page_number": 2,
    "excerpt": "TAB. RACIPER 40MG 1-0-0 7 DAYS (BEFORE FOOD)",
    "status": "verified",
    "confidence": 1.0,
    "readable": true,
    "identity_compatible": true,
    "conflict_ids": []
  },
  {
    "evidence_id": "ev-c755b4d8",
    "category": "medication",
    "value": "TAB. EMESET",
    "source_file": "patient 2 (1).pdf",
    "page_number": 2,
    "excerpt": "TAB. EMESET 4MG 1-1-1 3 DAYS",
    "status": "verified",
    "confidence": 1.0,
    "readable": true,
    "identity_compatible": true,
    "conflict_ids": []
  },
  {
    "evidence_id": "ev-2f1a3e00",
    "category": "medication",
    "value": "TAB. OFLOX TZ",
    "source_file": "patient 2 (1).pdf",
    "page_number": 2,
    "excerpt": "TAB. OFLOX TZ 1-0-1 5 DAYS",
    "status": "verified",
    "confidence": 1.0,
    "readable": true,
    "identity_compatible": true,
    "conflict_ids": []
  },
  {
    "evidence_id": "ev-c0ea3270",
    "category": "medication",
    "value": "TAB M STRONG",
    "source_file": "patient 2 (1).pdf",
    "page_number": 2,
    "excerpt": "TAB M STRONG 1-0-0 15 DAYS",
    "status": "verified",
    "confidence": 1.0,
    "readable": true,
    "identity_compatible": true,
    "conflict_ids": []
  },
  {
    "evidence_id": "ev-f70bc1a7",
    "category": "medication",
    "value": "TAB. ZEDOTT",
    "source_file": "patient 2 (1).pdf",
    "page_number": 2,
    "excerpt": "TAB. ZEDOTT 1-1-1 3 DAYS",
    "status": "verified",
    "confidence": 1.0,
    "readable": true,
    "identity_compatible": true,
    "conflict_ids": []
  },
  {
    "evidence_id": "ev-aa63eacd",
    "category": "medication",
    "value": "TAB. ENTRC",
    "source_file": "patient 2 (1).pdf",
    "page_number": 2,
    "excerpt": "TAB. ENTRC 1-0-1 3 DAYS",
    "status": "verified",
    "confidence": 1.0,
    "readable": true,
    "identity_compatible": true,
    "conflict_ids": []
  },
  {
    "evidence_id": "ev-43ec813c",
    "category": "medication",
    "value": "TAB. MEFTAL SPAS",
    "source_file": "patient 2 (1).pdf",
    "page_number": 2,
    "excerpt": "TAB. MEFTAL SPAS 1 TAB SOS 4 TABLETS",
    "status": "verified",
    "confidence": 1.0,
    "readable": true,
    "identity_compatible": true,
    "conflict_ids": []
  },
  {
    "evidence_id": "ev-a47d1d7b",
    "category": "medication",
    "value": "TAB. LOPIRAMIDE",
    "source_file": "patient 2 (1).pdf",
    "page_number": 2,
    "excerpt": "TAB. LOPIRAMIDE 2MG 1-0-1 5 DAYS",
    "status": "verified",
    "confidence": 1.0,
    "readable": true,
    "identity_compatible": true,
    "conflict_ids": []
  },
  {
    "evidence_id": "ev-2436e9a2",
    "category": "principal_diagnosis",
    "value": "DKA",
    "source_file": "patient 2 (1).pdf",
    "page_number": 3,
    "excerpt": "DKA",
    "status": "conflicting",
    "confidence": 1.0,
    "readable": true,
    "identity_compatible": true,
    "conflict_ids": [
      "conflict-73bf9888"
    ]
  },
  {
    "evidence_id": "ev-adf2d0cb",
    "category": "clinical_context",
    "value": "Triage Category Yellow",
    "source_file": "patient 2 (1).pdf",
    "page_number": 3,
    "excerpt": "Yellow",
    "status": "verified",
    "confidence": 1.0,
    "readable": true,
    "identity_compatible": true,
    "conflict_ids": []
  },
  {
    "evidence_id": "ev-f562b359",
    "category": "hospital_course",
    "value": "Pulse 116 b/m",
    "source_file": "patient 2 (1).pdf",
    "page_number": 3,
    "excerpt": "Pulse 116 b/m",
    "status": "verified",
    "confidence": 1.0,
    "readable": true,
    "identity_compatible": true,
    "conflict_ids": []
  },
  {
    "evidence_id": "ev-56376296",
    "category": "hospital_course",
    "value": "BP 87/50",
    "source_file": "patient 2 (1).pdf",
    "page_number": 3,
    "excerpt": "BP 87/50",
    "status": "verified",
    "confidence": 1.0,
    "readable": true,
    "identity_compatible": true,
    "conflict_ids": []
  },
  {
    "evidence_id": "ev-e7bce961",
    "category": "hospital_course",
    "value": "Temp 98\u00b0F",
    "source_file": "patient 2 (1).pdf",
    "page_number": 3,
    "excerpt": "Temp 98\u00b0F",
    "status": "verified",
    "confidence": 1.0,
    "readable": true,
    "identity_compatible": true,
    "conflict_ids": []
  },
  {
    "evidence_id": "ev-f4d7a3aa",
    "category": "hospital_course",
    "value": "SaO2 on air 96%",
    "source_file": "patient 2 (1).pdf",
    "page_number": 3,
    "excerpt": "SaO2 on air 96%",
    "status": "verified",
    "confidence": 1.0,
    "readable": true,
    "identity_compatible": true,
    "conflict_ids": []
  },
  {
    "evidence_id": "ev-126dcd04",
    "category": "hospital_course",
    "value": "GCS 15/15",
    "source_file": "patient 2 (1).pdf",
    "page_number": 3,
    "excerpt": "GCS 15/15",
    "status": "verified",
    "confidence": 1.0,
    "readable": true,
    "identity_compatible": true,
    "conflict_ids": []
  },
  {
    "evidence_id": "ev-ca105178",
    "category": "hospital_course",
    "value": "RR 22 b/m",
    "source_file": "patient 2 (1).pdf",
    "page_number": 3,
    "excerpt": "RR 22 b/m",
    "status": "verified",
    "confidence": 1.0,
    "readable": true,
    "identity_compatible": true,
    "conflict_ids": []
  },
  {
    "evidence_id": "ev-31cd8731",
    "category": "hospital_course",
    "value": "Blood Glucose 443 mg/dl",
    "source_file": "patient 2 (1).pdf",
    "page_number": 3,
    "excerpt": "Blood Glucose 443 mg/dl",
    "status": "verified",
    "confidence": 1.0,
    "readable": true,
    "identity_compatible": true,
    "conflict_ids": []
  },
  {
    "evidence_id": "ev-32691a64",
    "category": "hospital_course",
    "value": "Pain score 4/10",
    "source_file": "patient 2 (1).pdf",
    "page_number": 3,
    "excerpt": "Pain score 4/10",
    "status": "verified",
    "confidence": 1.0,
    "readable": true,
    "identity_compatible": true,
    "conflict_ids": []
  },
  {
    "evidence_id": "ev-18259771",
    "category": "procedure",
    "value": "IV Canulization done in left hand 20g",
    "source_file": "patient 2 (1).pdf",
    "page_number": 3,
    "excerpt": "IV Canulization done in left hand 20g",
    "status": "verified",
    "confidence": 1.0,
    "readable": true,
    "identity_compatible": true,
    "conflict_ids": []
  },
  {
    "evidence_id": "ev-6e2bc1f8",
    "category": "pending_result",
    "value": "CBL, creat, SE",
    "source_file": "patient 2 (1).pdf",
    "page_number": 3,
    "excerpt": "CBL, creat, SE",
    "status": "pending",
    "confidence": 1.0,
    "readable": true,
    "identity_compatible": true,
    "conflict_ids": []
  },
  {
    "evidence_id": "ev-d8baacb1",
    "category": "pending_result",
    "value": "ABG, urine",
    "source_file": "patient 2 (1).pdf",
    "page_number": 3,
    "excerpt": "ABG, urine",
    "status": "pending",
    "confidence": 1.0,
    "readable": true,
    "identity_compatible": true,
    "conflict_ids": []
  },
  {
    "evidence_id": "ev-40e7f477",
    "category": "pending_result",
    "value": "Ech",
    "source_file": "patient 2 (1).pdf",
    "page_number": 3,
    "excerpt": "Ech",
    "status": "verified",
    "confidence": 1.0,
    "readable": true,
    "identity_compatible": true,
    "conflict_ids": []
  },
  {
    "evidence_id": "ev-ad834c3a",
    "category": "clinical_context",
    "value": "Patient advised admission to ward/ICU",
    "source_file": "patient 2 (1).pdf",
    "page_number": 4,
    "excerpt": "Patient advised admission to ward/ICU",
    "status": "verified",
    "confidence": 1.0,
    "readable": true,
    "identity_compatible": true,
    "conflict_ids": []
  },
  {
    "evidence_id": "ev-1336af76",
    "category": "medication",
    "value": "NS",
    "source_file": "patient 2 (1).pdf",
    "page_number": 4,
    "excerpt": "INF NS 2 Bolus 6:14pm 9:00pm",
    "status": "verified",
    "confidence": 1.0,
    "readable": true,
    "identity_compatible": true,
    "conflict_ids": []
  },
  {
    "evidence_id": "ev-6ad4de61",
    "category": "medication",
    "value": "PAN",
    "source_file": "patient 2 (1).pdf",
    "page_number": 4,
    "excerpt": "INJ PAN 40mg IV 6:14pm",
    "status": "verified",
    "confidence": 1.0,
    "readable": true,
    "identity_compatible": true,
    "conflict_ids": []
  },
  {
    "evidence_id": "ev-bc24855e",
    "category": "medication",
    "value": "EMESET",
    "source_file": "patient 2 (1).pdf",
    "page_number": 4,
    "excerpt": "INJ EMESET 4mg IV 6:14pm",
    "status": "verified",
    "confidence": 1.0,
    "readable": true,
    "identity_compatible": true,
    "conflict_ids": []
  },
  {
    "evidence_id": "ev-ef6feca8",
    "category": "pending_result",
    "value": "CBC",
    "source_file": "patient 2 (1).pdf",
    "page_number": 5,
    "excerpt": "1/3/20 7pm CBC an form",
    "status": "verified",
    "confidence": 1.0,
    "readable": true,
    "identity_compatible": true,
    "conflict_ids": []
  },
  {
    "evidence_id": "ev-63343330",
    "category": "pending_result",
    "value": "S. Creus",
    "source_file": "patient 2 (1).pdf",
    "page_number": 5,
    "excerpt": "S. Creus",
    "status": "verified",
    "confidence": 0.6,
    "readable": true,
    "identity_compatible": true,
    "conflict_ids": []
  },
  {
    "evidence_id": "ev-ec8b5369",
    "category": "clinical_context",
    "value": "Hb 10.4 gm/dl on 28/2/26",
    "source_file": "patient 2 (1).pdf",
    "page_number": 6,
    "excerpt": "10.4 gm/dl",
    "status": "verified",
    "confidence": 1.0,
    "readable": true,
    "identity_compatible": true,
    "conflict_ids": []
  },
  {
    "evidence_id": "ev-71bd8426",
    "category": "clinical_context",
    "value": "Hb 10.7 gm/dl on 1/3/26",
    "source_file": "patient 2 (1).pdf",
    "page_number": 6,
    "excerpt": "10.7 gm/dl",
    "status": "verified",
    "confidence": 1.0,
    "readable": true,
    "identity_compatible": true,
    "conflict_ids": []
  },
  {
    "evidence_id": "ev-24dd26b2",
    "category": "clinical_context",
    "value": "TLC 7820 cells/cmm on 28/2/26",
    "source_file": "patient 2 (1).pdf",
    "page_number": 6,
    "excerpt": "7820 cells/cmm",
    "status": "verified",
    "confidence": 1.0,
    "readable": true,
    "identity_compatible": true,
    "conflict_ids": []
  },
  {
    "evidence_id": "ev-1b2ebec5",
    "category": "clinical_context",
    "value": "TLC 11560 cells/cmm on 1/3/26",
    "source_file": "patient 2 (1).pdf",
    "page_number": 6,
    "excerpt": "11560 cells/cmm",
    "status": "verified",
    "confidence": 1.0,
    "readable": true,
    "identity_compatible": true,
    "conflict_ids": []
  },
  {
    "evidence_id": "ev-99c7dcbb",
    "category": "clinical_context",
    "value": "PLAT 1.28 lac/cmm on 28/2/26",
    "source_file": "patient 2 (1).pdf",
    "page_number": 6,
    "excerpt": "1.28 lac/cmm",
    "status": "verified",
    "confidence": 1.0,
    "readable": true,
    "identity_compatible": true,
    "conflict_ids": []
  },
  {
    "evidence_id": "ev-36e2e26d",
    "category": "clinical_context",
    "value": "PLAT 1.60 lac/cmm on 1/3/26",
    "source_file": "patient 2 (1).pdf",
    "page_number": 6,
    "excerpt": "1.60 lac/cmm",
    "status": "verified",
    "confidence": 1.0,
    "readable": true,
    "identity_compatible": true,
    "conflict_ids": []
  },
  {
    "evidence_id": "ev-03306176",
    "category": "clinical_context",
    "value": "Creatinine 1.03 mg/dl on 28/2/26",
    "source_file": "patient 2 (1).pdf",
    "page_number": 6,
    "excerpt": "1.03 mg/dl",
    "status": "verified",
    "confidence": 1.0,
    "readable": true,
    "identity_compatible": true,
    "conflict_ids": []
  },
  {
    "evidence_id": "ev-ac219291",
    "category": "clinical_context",
    "value": "Creatinine 1.04 mg/dl on 1/3/26",
    "source_file": "patient 2 (1).pdf",
    "page_number": 6,
    "excerpt": "1.04 mg/dl",
    "status": "verified",
    "confidence": 1.0,
    "readable": true,
    "identity_compatible": true,
    "conflict_ids": []
  },
  {
    "evidence_id": "ev-96c09b3c",
    "category": "clinical_context",
    "value": "27/2/20",
    "source_file": "patient 2 (1).pdf",
    "page_number": 7,
    "excerpt": "Date: 27/2/20",
    "status": "verified",
    "confidence": 1.0,
    "readable": true,
    "identity_compatible": true,
    "conflict_ids": []
  },
  {
    "evidence_id": "ev-fa756c97",
    "category": "hospital_course",
    "value": "Patient Hand over taken from Evening duty Staff to Night duty Staff.",
    "source_file": "patient 2 (1).pdf",
    "page_number": 7,
    "excerpt": "Patient Hand over taken from Evening duty Staff to Night duty Staff.",
    "status": "verified",
    "confidence": 1.0,
    "readable": true,
    "identity_compatible": true,
    "conflict_ids": []
  },
  {
    "evidence_id": "ev-541e08bc",
    "category": "hospital_course",
    "value": "Bed Rounds done",
    "source_file": "patient 2 (1).pdf",
    "page_number": 7,
    "excerpt": "Patient Bed Rounds done",
    "status": "verified",
    "confidence": 1.0,
    "readable": true,
    "identity_compatible": true,
    "conflict_ids": []
  },
  {
    "evidence_id": "ev-de490ef7",
    "category": "hospital_course",
    "value": "Conscious and Oriented",
    "source_file": "patient 2 (1).pdf",
    "page_number": 7,
    "excerpt": "Patient Conscious and Oriented",
    "status": "verified",
    "confidence": 1.0,
    "readable": true,
    "identity_compatible": true,
    "conflict_ids": []
  },
  {
    "evidence_id": "ev-8119786b",
    "category": "hospital_course",
    "value": "IV cannula present",
    "source_file": "patient 2 (1).pdf",
    "page_number": 7,
    "excerpt": "Patient IV cannula present.",
    "status": "verified",
    "confidence": 1.0,
    "readable": true,
    "identity_compatible": true,
    "conflict_ids": []
  },
  {
    "evidence_id": "ev-f1407934",
    "category": "hospital_course",
    "value": "Foley's catheter present",
    "source_file": "patient 2 (1).pdf",
    "page_number": 7,
    "excerpt": "Patient Foley's catheter present.",
    "status": "verified",
    "confidence": 1.0,
    "readable": true,
    "identity_compatible": true,
    "conflict_ids": []
  },
  {
    "evidence_id": "ev-68669cc5",
    "category": "hospital_course",
    "value": "IV FNS 1000ml 1hr on flow",
    "source_file": "patient 2 (1).pdf",
    "page_number": 7,
    "excerpt": "Patient IV FNS 1000ml 1hr on flow.",
    "status": "verified",
    "confidence": 1.0,
    "readable": true,
    "identity_compatible": true,
    "conflict_ids": []
  },
  {
    "evidence_id": "ev-2aabfc40",
    "category": "hospital_course",
    "value": "2nd hourly GRBS monitoring present",
    "source_file": "patient 2 (1).pdf",
    "page_number": 7,
    "excerpt": "Patient 2nd hourly GRBS monitoring present",
    "status": "verified",
    "confidence": 1.0,
    "readable": true,
    "identity_compatible": true,
    "conflict_ids": []
  },
  {
    "evidence_id": "ev-494503d7",
    "category": "hospital_course",
    "value": "Vital Signs monitored",
    "source_file": "patient 2 (1).pdf",
    "page_number": 7,
    "excerpt": "Patient Vital Signs monitored",
    "status": "verified",
    "confidence": 1.0,
    "readable": true,
    "identity_compatible": true,
    "conflict_ids": []
  },
  {
    "evidence_id": "ev-e60c46a6",
    "category": "hospital_course",
    "value": "Temp: 98\u00b0F",
    "source_file": "patient 2 (1).pdf",
    "page_number": 7,
    "excerpt": "Temp: 98\u00b0F",
    "status": "verified",
    "confidence": 1.0,
    "readable": true,
    "identity_compatible": true,
    "conflict_ids": []
  },
  {
    "evidence_id": "ev-b2dce7e2",
    "category": "hospital_course",
    "value": "Bp: 110/80 mmHg",
    "source_file": "patient 2 (1).pdf",
    "page_number": 7,
    "excerpt": "Bp: 110/80 mmHg",
    "status": "verified",
    "confidence": 0.9,
    "readable": true,
    "identity_compatible": true,
    "conflict_ids": []
  },
  {
    "evidence_id": "ev-1d512d16",
    "category": "hospital_course",
    "value": "HR: 85 bt/min",
    "source_file": "patient 2 (1).pdf",
    "page_number": 7,
    "excerpt": "HR: 85 bt/min",
    "status": "verified",
    "confidence": 1.0,
    "readable": true,
    "identity_compatible": true,
    "conflict_ids": []
  },
  {
    "evidence_id": "ev-03dedf97",
    "category": "hospital_course",
    "value": "PR: 23 br/min",
    "source_file": "patient 2 (1).pdf",
    "page_number": 7,
    "excerpt": "PR: 23 br/min",
    "status": "verified",
    "confidence": 1.0,
    "readable": true,
    "identity_compatible": true,
    "conflict_ids": []
  },
  {
    "evidence_id": "ev-c682afc3",
    "category": "hospital_course",
    "value": "Spo2: 98%",
    "source_file": "patient 2 (1).pdf",
    "page_number": 7,
    "excerpt": "Spo2: 98%",
    "status": "verified",
    "confidence": 1.0,
    "readable": true,
    "identity_compatible": true,
    "conflict_ids": []
  },
  {
    "evidence_id": "ev-feff1bbe",
    "category": "procedure",
    "value": "CT KUB plan",
    "source_file": "patient 2 (1).pdf",
    "page_number": 7,
    "excerpt": "Patient CT KUB plan",
    "status": "verified",
    "confidence": 1.0,
    "readable": true,
    "identity_compatible": true,
    "conflict_ids": []
  },
  {
    "evidence_id": "ev-a712fe9c",
    "category": "hospital_course",
    "value": "Foley's catheter clamped as per advice Dr.",
    "source_file": "patient 2 (1).pdf",
    "page_number": 7,
    "excerpt": "Foley's catheter clamped as per advice Dr.",
    "status": "verified",
    "confidence": 1.0,
    "readable": true,
    "identity_compatible": true,
    "conflict_ids": []
  },
  {
    "evidence_id": "ev-28f132fe",
    "category": "hospital_course",
    "value": "orally soft diet taken",
    "source_file": "patient 2 (1).pdf",
    "page_number": 7,
    "excerpt": "Patient orally soft diet taken",
    "status": "verified",
    "confidence": 1.0,
    "readable": true,
    "identity_compatible": true,
    "conflict_ids": []
  },
  {
    "evidence_id": "ev-fe538698",
    "category": "hospital_course",
    "value": "one episode of chills and Tachycardia",
    "source_file": "patient 2 (1).pdf",
    "page_number": 7,
    "excerpt": "Patient had one episode of chills and Tachycardia",
    "status": "verified",
    "confidence": 1.0,
    "readable": true,
    "identity_compatible": true,
    "conflict_ids": []
  },
  {
    "evidence_id": "ev-8fd1ac0a",
    "category": "hospital_course",
    "value": "Informed to Dr. and advice given.",
    "source_file": "patient 2 (1).pdf",
    "page_number": 7,
    "excerpt": "Informed to Dr. and advice given.",
    "status": "verified",
    "confidence": 1.0,
    "readable": true,
    "identity_compatible": true,
    "conflict_ids": []
  },
  {
    "evidence_id": "ev-b89cc790",
    "category": "medication",
    "value": "Tramadol",
    "source_file": "patient 2 (1).pdf",
    "page_number": 7,
    "excerpt": "Inj. Tramadol 2ml + 3ml NS = 5ml 3ml IV as per advice given.",
    "status": "verified",
    "confidence": 1.0,
    "readable": true,
    "identity_compatible": true,
    "conflict_ids": []
  },
  {
    "evidence_id": "ev-f717030b",
    "category": "clinical_context",
    "value": "27/2/26",
    "source_file": "patient 2 (1).pdf",
    "page_number": 8,
    "excerpt": "27/2/26",
    "status": "verified",
    "confidence": 1.0,
    "readable": true,
    "identity_compatible": true,
    "conflict_ids": []
  },
  {
    "evidence_id": "ev-5ea6006b",
    "category": "procedure",
    "value": "CT KUB cancelled",
    "source_file": "patient 2 (1).pdf",
    "page_number": 8,
    "excerpt": "Patient CT KUB cancelled due in Night duty time due to patient's condition's",
    "status": "verified",
    "confidence": 1.0,
    "readable": true,
    "identity_compatible": true,
    "conflict_ids": []
  },
  {
    "evidence_id": "ev-54d0cb08",
    "category": "hospital_course",
    "value": "fever Spike Temp-103F",
    "source_file": "patient 2 (1).pdf",
    "page_number": 8,
    "excerpt": "Patient had a fever Spike Temp-103F",
    "status": "verified",
    "confidence": 1.0,
    "readable": true,
    "identity_compatible": true,
    "conflict_ids": []
  },
  {
    "evidence_id": "ev-d2e44e81",
    "category": "hospital_course",
    "value": "Patient was settled",
    "source_file": "patient 2 (1).pdf",
    "page_number": 8,
    "excerpt": "Patient was settled",
    "status": "verified",
    "confidence": 1.0,
    "readable": true,
    "identity_compatible": true,
    "conflict_ids": []
  },
  {
    "evidence_id": "ev-bb29bd25",
    "category": "hospital_course",
    "value": "had a Good Sleep",
    "source_file": "patient 2 (1).pdf",
    "page_number": 8,
    "excerpt": "Patient had a Good Sleep.",
    "status": "verified",
    "confidence": 1.0,
    "readable": true,
    "identity_compatible": true,
    "conflict_ids": []
  },
  {
    "evidence_id": "ev-72118b6f",
    "category": "hospital_course",
    "value": "Bed bath Given, Bed making done, comfortable position given.",
    "source_file": "patient 2 (1).pdf",
    "page_number": 8,
    "excerpt": "Patient Bed bath Given, Bed making done, comfortable position given.",
    "status": "verified",
    "confidence": 1.0,
    "readable": true,
    "identity_compatible": true,
    "conflict_ids": []
  },
  {
    "evidence_id": "ev-9fc2227d",
    "category": "hospital_course",
    "value": "bowel opened",
    "source_file": "patient 2 (1).pdf",
    "page_number": 8,
    "excerpt": "Patient bowel opened.",
    "status": "verified",
    "confidence": 1.0,
    "readable": true,
    "identity_compatible": true,
    "conflict_ids": []
  },
  {
    "evidence_id": "ev-9c1480ba",
    "category": "hospital_course",
    "value": "GRBS checked and recorded in chart",
    "source_file": "patient 2 (1).pdf",
    "page_number": 8,
    "excerpt": "Patient GRBS checked and recorded in chart",
    "status": "verified",
    "confidence": 1.0,
    "readable": true,
    "identity_compatible": true,
    "conflict_ids": []
  },
  {
    "evidence_id": "ev-641c3e17",
    "category": "hospital_course",
    "value": "Hand over Given to Morning duty Staff",
    "source_file": "patient 2 (1).pdf",
    "page_number": 8,
    "excerpt": "Patient Hand over Given to Morning duty Staff",
    "status": "verified",
    "confidence": 1.0,
    "readable": true,
    "identity_compatible": true,
    "conflict_ids": []
  },
  {
    "evidence_id": "ev-471969f0",
    "category": "medication",
    "value": "Inj-PCT",
    "source_file": "patient 2 (1).pdf",
    "page_number": 8,
    "excerpt": "Inj-PCT 1gm asper advice given",
    "status": "verified",
    "confidence": 1.0,
    "readable": true,
    "identity_compatible": true,
    "conflict_ids": []
  },
  {
    "evidence_id": "ev-f04d6503",
    "category": "medication",
    "value": "Inj-Emeset",
    "source_file": "patient 2 (1).pdf",
    "page_number": 8,
    "excerpt": "Inj-Emeset tmg",
    "status": "verified",
    "confidence": 1.0,
    "readable": true,
    "identity_compatible": true,
    "conflict_ids": []
  },
  {
    "evidence_id": "ev-e8cb2e4f",
    "category": "medication",
    "value": "Inj-PAN",
    "source_file": "patient 2 (1).pdf",
    "page_number": 8,
    "excerpt": "Inj-PAN komg",
    "status": "verified",
    "confidence": 1.0,
    "readable": true,
    "identity_compatible": true,
    "conflict_ids": []
  },
  {
    "evidence_id": "ev-cff6602d",
    "category": "medication",
    "value": "Inj-Meropenem",
    "source_file": "patient 2 (1).pdf",
    "page_number": 8,
    "excerpt": "Inj-Meropenem 1gm",
    "status": "verified",
    "confidence": 1.0,
    "readable": true,
    "identity_compatible": true,
    "conflict_ids": []
  },
  {
    "evidence_id": "ev-023563bd",
    "category": "medication",
    "value": "Inj-Happy Nove",
    "source_file": "patient 2 (1).pdf",
    "page_number": 8,
    "excerpt": "Inj-Happy Nove plus IV given",
    "status": "verified",
    "confidence": 1.0,
    "readable": true,
    "identity_compatible": true,
    "conflict_ids": []
  },
  {
    "evidence_id": "ev-b3151687",
    "category": "clinical_context",
    "value": "Date of documentation: 28/2/26",
    "source_file": "patient 2 (1).pdf",
    "page_number": 9,
    "excerpt": "Date: 28/2/26",
    "status": "verified",
    "confidence": 1.0,
    "readable": true,
    "identity_compatible": true,
    "conflict_ids": []
  },
  {
    "evidence_id": "ev-b93532d3",
    "category": "clinical_context",
    "value": "Shift from 8 AM to 2 PM",
    "source_file": "patient 2 (1).pdf",
    "page_number": 9,
    "excerpt": "From... 8.Am to... 2pm...",
    "status": "verified",
    "confidence": 1.0,
    "readable": true,
    "identity_compatible": true,
    "conflict_ids": []
  },
  {
    "evidence_id": "ev-73665235",
    "category": "clinical_context",
    "value": "Patient charge handover taken from night duty",
    "source_file": "patient 2 (1).pdf",
    "page_number": 9,
    "excerpt": "patient charge hand over taken from Night duty",
    "status": "verified",
    "confidence": 1.0,
    "readable": true,
    "identity_compatible": true,
    "conflict_ids": []
  },
  {
    "evidence_id": "ev-8c02f81c",
    "category": "clinical_context",
    "value": "Staff on monitor duty",
    "source_file": "patient 2 (1).pdf",
    "page_number": 9,
    "excerpt": "Staff DD monitor duty",
    "status": "verified",
    "confidence": 0.8,
    "readable": true,
    "identity_compatible": true,
    "conflict_ids": []
  },
  {
    "evidence_id": "ev-91aa2edc",
    "category": "clinical_context",
    "value": "Patient side rounds done",
    "source_file": "patient 2 (1).pdf",
    "page_number": 9,
    "excerpt": "patient side rounds is Done",
    "status": "verified",
    "confidence": 1.0,
    "readable": true,
    "identity_compatible": true,
    "conflict_ids": []
  },
  {
    "evidence_id": "ev-6d94c54b",
    "category": "clinical_context",
    "value": "Patient vital signs checked and recorded",
    "source_file": "patient 2 (1).pdf",
    "page_number": 9,
    "excerpt": "patient vital sings checd and record",
    "status": "verified",
    "confidence": 1.0,
    "readable": true,
    "identity_compatible": true,
    "conflict_ids": []
  },
  {
    "evidence_id": "ev-2750f41b",
    "category": "clinical_context",
    "value": "Blood Pressure: 120/80 mmHg",
    "source_file": "patient 2 (1).pdf",
    "page_number": 9,
    "excerpt": "Bp - 120/80 mmHq",
    "status": "verified",
    "confidence": 1.0,
    "readable": true,
    "identity_compatible": true,
    "conflict_ids": []
  },
  {
    "evidence_id": "ev-38bdfe22",
    "category": "clinical_context",
    "value": "SpO2: 98%",
    "source_file": "patient 2 (1).pdf",
    "page_number": 9,
    "excerpt": "Spo2 - 98%",
    "status": "verified",
    "confidence": 1.0,
    "readable": true,
    "identity_compatible": true,
    "conflict_ids": []
  },
  {
    "evidence_id": "ev-cfa97f8b",
    "category": "clinical_context",
    "value": "Heart Rate: 65 beats/min",
    "source_file": "patient 2 (1).pdf",
    "page_number": 9,
    "excerpt": "HR - 65 b/m",
    "status": "verified",
    "confidence": 1.0,
    "readable": true,
    "identity_compatible": true,
    "conflict_ids": []
  },
  {
    "evidence_id": "ev-bd2f08f8",
    "category": "clinical_context",
    "value": "Respiratory Rate: 20 breaths/min",
    "source_file": "patient 2 (1).pdf",
    "page_number": 9,
    "excerpt": "RR - 20 b/m",
    "status": "verified",
    "confidence": 1.0,
    "readable": true,
    "identity_compatible": true,
    "conflict_ids": []
  },
  {
    "evidence_id": "ev-c5169c5f",
    "category": "clinical_context",
    "value": "IV Cannula present",
    "source_file": "patient 2 (1).pdf",
    "page_number": 9,
    "excerpt": "patient IV Cannula present (F)",
    "status": "verified",
    "confidence": 1.0,
    "readable": true,
    "identity_compatible": true,
    "conflict_ids": []
  },
  {
    "evidence_id": "ev-1575fc59",
    "category": "clinical_context",
    "value": "Foley catheter present",
    "source_file": "patient 2 (1).pdf",
    "page_number": 9,
    "excerpt": "patient Foleys present (P)",
    "status": "verified",
    "confidence": 1.0,
    "readable": true,
    "identity_compatible": true,
    "conflict_ids": []
  },
  {
    "evidence_id": "ev-6963a58a",
    "category": "clinical_context",
    "value": "I/O monitored",
    "source_file": "patient 2 (1).pdf",
    "page_number": 9,
    "excerpt": "patient I/O monitor",
    "status": "verified",
    "confidence": 1.0,
    "readable": true,
    "identity_compatible": true,
    "conflict_ids": []
  },
  {
    "evidence_id": "ev-72b65c92",
    "category": "clinical_context",
    "value": "Patient in comfortable position",
    "source_file": "patient 2 (1).pdf",
    "page_number": 9,
    "excerpt": "patient comfortable position",
    "status": "verified",
    "confidence": 1.0,
    "readable": true,
    "identity_compatible": true,
    "conflict_ids": []
  },
  {
    "evidence_id": "ev-f44ecdcc",
    "category": "procedure",
    "value": "CT KUB done",
    "source_file": "patient 2 (1).pdf",
    "page_number": 9,
    "excerpt": "patient CT KUD is Done",
    "status": "verified",
    "confidence": 0.9,
    "readable": true,
    "identity_compatible": true,
    "conflict_ids": []
  },
  {
    "evidence_id": "ev-475d1927",
    "category": "clinical_context",
    "value": "File is done",
    "source_file": "patient 2 (1).pdf",
    "page_number": 9,
    "excerpt": "file is Done",
    "status": "verified",
    "confidence": 1.0,
    "readable": true,
    "identity_compatible": true,
    "conflict_ids": []
  },
  {
    "evidence_id": "ev-9df766a7",
    "category": "clinical_context",
    "value": "IV fluids 150ml per hour ongoing",
    "source_file": "patient 2 (1).pdf",
    "page_number": 9,
    "excerpt": "patient IV fluids 150ml per hour on going",
    "status": "verified",
    "confidence": 1.0,
    "readable": true,
    "identity_compatible": true,
    "conflict_ids": []
  },
  {
    "evidence_id": "ev-93689e73",
    "category": "clinical_context",
    "value": "Patient seen by Dr Chemash, note added to shift to ward",
    "source_file": "patient 2 (1).pdf",
    "page_number": 9,
    "excerpt": "patient seen by Dr Chemash sig ADD to Shif to word.",
    "status": "verified",
    "confidence": 0.9,
    "readable": true,
    "identity_compatible": true,
    "conflict_ids": []
  },
  {
    "evidence_id": "ev-dce91ac6",
    "category": "clinical_context",
    "value": "Date of note: 28/2/28",
    "source_file": "patient 2 (1).pdf",
    "page_number": 10,
    "excerpt": "Date: 28/2/28",
    "status": "verified",
    "confidence": 1.0,
    "readable": true,
    "identity_compatible": true,
    "conflict_ids": []
  },
  {
    "evidence_id": "ev-a9c97080",
    "category": "clinical_context",
    "value": "Time of note: 8am to 2pm",
    "source_file": "patient 2 (1).pdf",
    "page_number": 10,
    "excerpt": "From...8am to 2pm...",
    "status": "verified",
    "confidence": 0.9,
    "readable": true,
    "identity_compatible": true,
    "conflict_ids": []
  },
  {
    "evidence_id": "ev-c580820f",
    "category": "hospital_course",
    "value": "Patient seen by Dr Sin Adv",
    "source_file": "patient 2 (1).pdf",
    "page_number": 10,
    "excerpt": "patient Seen By Dr Sin Adv",
    "status": "verified",
    "confidence": 0.9,
    "readable": true,
    "identity_compatible": true,
    "conflict_ids": []
  },
  {
    "evidence_id": "ev-d1280dc1",
    "category": "pending_result",
    "value": "CBC",
    "source_file": "patient 2 (1).pdf",
    "page_number": 10,
    "excerpt": "'CBC'",
    "status": "verified",
    "confidence": 0.8,
    "readable": true,
    "identity_compatible": true,
    "conflict_ids": []
  },
  {
    "evidence_id": "ev-6ded27a8",
    "category": "hospital_course",
    "value": "Patient shifted to ward",
    "source_file": "patient 2 (1).pdf",
    "page_number": 10,
    "excerpt": "patient sly to word due",
    "status": "verified",
    "confidence": 0.9,
    "readable": true,
    "identity_compatible": true,
    "conflict_ids": []
  },
  {
    "evidence_id": "ev-525c7c2d",
    "category": "hospital_course",
    "value": "Patient given Campus 10 unit",
    "source_file": "patient 2 (1).pdf",
    "page_number": 10,
    "excerpt": "patient By- Campus 10 unit given",
    "status": "verified",
    "confidence": 0.7,
    "readable": true,
    "identity_compatible": true,
    "conflict_ids": []
  },
  {
    "evidence_id": "ev-10a879db",
    "category": "hospital_course",
    "value": "All report handover given to ward staff",
    "source_file": "patient 2 (1).pdf",
    "page_number": 10,
    "excerpt": "patient all report hand over given to word staff",
    "status": "verified",
    "confidence": 0.9,
    "readable": true,
    "identity_compatible": true,
    "conflict_ids": []
  },
  {
    "evidence_id": "ev-55d3ea6e",
    "category": "clinical_context",
    "value": "GRBS is checked",
    "source_file": "patient 2 (1).pdf",
    "page_number": 10,
    "excerpt": "patient GRBS is check",
    "status": "verified",
    "confidence": 0.9,
    "readable": true,
    "identity_compatible": true,
    "conflict_ids": []
  },
  {
    "evidence_id": "ev-9b1beb16",
    "category": "hospital_course",
    "value": "Patient charge handover given to staff",
    "source_file": "patient 2 (1).pdf",
    "page_number": 10,
    "excerpt": "pt charge hand over given to SDIEW staff to word staff",
    "status": "verified",
    "confidence": 0.8,
    "readable": true,
    "identity_compatible": true,
    "conflict_ids": []
  },
  {
    "evidence_id": "ev-7e1308e0",
    "category": "medication",
    "value": "IV medication",
    "source_file": "patient 2 (1).pdf",
    "page_number": 10,
    "excerpt": "patient IV medication given as per dry chat",
    "status": "verified",
    "confidence": 1.0,
    "readable": true,
    "identity_compatible": true,
    "conflict_ids": []
  },
  {
    "evidence_id": "ev-b05b507f",
    "category": "clinical_context",
    "value": "26/2/20 @ 8pm TO 8AM",
    "source_file": "patient 2 (1).pdf",
    "page_number": 11,
    "excerpt": "26/2/20 @ 8pm TO 8AM",
    "status": "verified",
    "confidence": 1.0,
    "readable": true,
    "identity_compatible": true,
    "conflict_ids": []
  },
  {
    "evidence_id": "ev-de73b096",
    "category": "clinical_context",
    "value": "No bed Sore",
    "source_file": "patient 2 (1).pdf",
    "page_number": 11,
    "excerpt": "-No bed Sore-",
    "status": "verified",
    "confidence": 1.0,
    "readable": true,
    "identity_compatible": true,
    "conflict_ids": []
  },
  {
    "evidence_id": "ev-035fe938",
    "category": "clinical_context",
    "value": "PULSES + -",
    "source_file": "patient 2 (1).pdf",
    "page_number": 11,
    "excerpt": "PULSES + -",
    "status": "verified",
    "confidence": 1.0,
    "readable": true,
    "identity_compatible": true,
    "conflict_ids": []
  },
  {
    "evidence_id": "ev-b4f58c37",
    "category": "hospital_course",
    "value": "No bed sores",
    "source_file": "patient 2 (1).pdf",
    "page_number": 12,
    "excerpt": "no bed sores",
    "status": "verified",
    "confidence": 1.0,
    "readable": true,
    "identity_compatible": true,
    "conflict_ids": []
  },
  {
    "evidence_id": "ev-1cdec19a",
    "category": "clinical_context",
    "value": "27/2/22 @ 8Am to 2pm",
    "source_file": "patient 2 (1).pdf",
    "page_number": 12,
    "excerpt": "27/2/22 @ 8Am to 2pm",
    "status": "verified",
    "confidence": 1.0,
    "readable": true,
    "identity_compatible": true,
    "conflict_ids": []
  },
  {
    "evidence_id": "ev-8e29ebeb",
    "category": "clinical_context",
    "value": "PULSES + -",
    "source_file": "patient 2 (1).pdf",
    "page_number": 12,
    "excerpt": "PULSES + -",
    "status": "verified",
    "confidence": 1.0,
    "readable": true,
    "identity_compatible": true,
    "conflict_ids": []
  },
  {
    "evidence_id": "ev-0bc57d24",
    "category": "patient_id",
    "value": "ASIDA 0327",
    "source_file": "patient 2 (1).pdf",
    "page_number": 13,
    "excerpt": "ASIDA 0327",
    "status": "verified",
    "confidence": 1.0,
    "readable": true,
    "identity_compatible": true,
    "conflict_ids": []
  },
  {
    "evidence_id": "ev-cda9a4f2",
    "category": "principal_diagnosis",
    "value": "BED SORES",
    "source_file": "patient 2 (1).pdf",
    "page_number": 13,
    "excerpt": "BED SORES",
    "status": "conflicting",
    "confidence": 1.0,
    "readable": true,
    "identity_compatible": true,
    "conflict_ids": [
      "conflict-73bf9888"
    ]
  },
  {
    "evidence_id": "ev-7f487f1c",
    "category": "clinical_context",
    "value": "PULSES + -",
    "source_file": "patient 2 (1).pdf",
    "page_number": 13,
    "excerpt": "PULSES + -",
    "status": "verified",
    "confidence": 1.0,
    "readable": true,
    "identity_compatible": true,
    "conflict_ids": []
  },
  {
    "evidence_id": "ev-f484873d",
    "category": "clinical_context",
    "value": "27/12/26",
    "source_file": "patient 2 (1).pdf",
    "page_number": 13,
    "excerpt": "27/12/26",
    "status": "verified",
    "confidence": 1.0,
    "readable": true,
    "identity_compatible": true,
    "conflict_ids": []
  },
  {
    "evidence_id": "ev-fcf1b8a0",
    "category": "clinical_context",
    "value": "2pm 8pm",
    "source_file": "patient 2 (1).pdf",
    "page_number": 13,
    "excerpt": "2pm 8pm",
    "status": "verified",
    "confidence": 1.0,
    "readable": true,
    "identity_compatible": true,
    "conflict_ids": []
  },
  {
    "evidence_id": "ev-d60fa7b3",
    "category": "hospital_course",
    "value": "No bed sores",
    "source_file": "patient 2 (1).pdf",
    "page_number": 14,
    "excerpt": "No bed sores",
    "status": "verified",
    "confidence": 1.0,
    "readable": true,
    "identity_compatible": true,
    "conflict_ids": []
  },
  {
    "evidence_id": "ev-9dafcbc0",
    "category": "hospital_course",
    "value": "PULSES + -",
    "source_file": "patient 2 (1).pdf",
    "page_number": 14,
    "excerpt": "PULSES + -",
    "status": "verified",
    "confidence": 1.0,
    "readable": true,
    "identity_compatible": true,
    "conflict_ids": []
  },
  {
    "evidence_id": "ev-6c4690d8",
    "category": "clinical_context",
    "value": "28/2/26 @ 8Am to 2pm",
    "source_file": "patient 2 (1).pdf",
    "page_number": 14,
    "excerpt": "28/2/26 @ 8Am to 2pm",
    "status": "verified",
    "confidence": 1.0,
    "readable": true,
    "identity_compatible": true,
    "conflict_ids": []
  },
  {
    "evidence_id": "ev-cd108a48",
    "category": "patient_name",
    "value": "J.K.G",
    "source_file": "patient 2 (1).pdf",
    "page_number": 15,
    "excerpt": "J.K.G",
    "status": "verified",
    "confidence": 1.0,
    "readable": true,
    "identity_compatible": true,
    "conflict_ids": []
  },
  {
    "evidence_id": "ev-c1b86dc1",
    "category": "clinical_context",
    "value": "Department: Internal Medicine",
    "source_file": "patient 2 (1).pdf",
    "page_number": 15,
    "excerpt": "Internal Medicine",
    "status": "verified",
    "confidence": 1.0,
    "readable": true,
    "identity_compatible": true,
    "conflict_ids": []
  },
  {
    "evidence_id": "ev-1735cc08",
    "category": "procedure",
    "value": "IV Cannulization (18-G) on 06/02/26",
    "source_file": "patient 2 (1).pdf",
    "page_number": 15,
    "excerpt": "Yes (18-G)",
    "status": "verified",
    "confidence": 1.0,
    "readable": true,
    "identity_compatible": true,
    "conflict_ids": []
  },
  {
    "evidence_id": "ev-74c1bb47",
    "category": "procedure",
    "value": "IV Cannulization (18-G) on 27/2/2",
    "source_file": "patient 2 (1).pdf",
    "page_number": 15,
    "excerpt": "Yes (18-G)",
    "status": "verified",
    "confidence": 1.0,
    "readable": true,
    "identity_compatible": true,
    "conflict_ids": []
  },
  {
    "evidence_id": "ev-111302c5",
    "category": "procedure",
    "value": "IV Cannulization (18-G) on 28/2/26",
    "source_file": "patient 2 (1).pdf",
    "page_number": 15,
    "excerpt": "Yes (18-G)",
    "status": "verified",
    "confidence": 1.0,
    "readable": true,
    "identity_compatible": true,
    "conflict_ids": []
  },
  {
    "evidence_id": "ev-8ffd9cb1",
    "category": "procedure",
    "value": "IV Cannulization (18-G) on 1/3/26",
    "source_file": "patient 2 (1).pdf",
    "page_number": 15,
    "excerpt": "Yes (18-G)",
    "status": "verified",
    "confidence": 1.0,
    "readable": true,
    "identity_compatible": true,
    "conflict_ids": []
  },
  {
    "evidence_id": "ev-fb3c5b06",
    "category": "procedure",
    "value": "IV Cannulization (21-G) on 2/3/26",
    "source_file": "patient 2 (1).pdf",
    "page_number": 15,
    "excerpt": "Yes (21-G)",
    "status": "verified",
    "confidence": 1.0,
    "readable": true,
    "identity_compatible": true,
    "conflict_ids": []
  },
  {
    "evidence_id": "ev-e0234cd1",
    "category": "procedure",
    "value": "Felley's Catheterisation (16F) on 06/02/26",
    "source_file": "patient 2 (1).pdf",
    "page_number": 15,
    "excerpt": "Yes 16F",
    "status": "verified",
    "confidence": 1.0,
    "readable": true,
    "identity_compatible": true,
    "conflict_ids": []
  },
  {
    "evidence_id": "ev-29b050d4",
    "category": "procedure",
    "value": "Felley's Catheterisation (16F) on 27/2/2",
    "source_file": "patient 2 (1).pdf",
    "page_number": 15,
    "excerpt": "Yes 16F",
    "status": "verified",
    "confidence": 1.0,
    "readable": true,
    "identity_compatible": true,
    "conflict_ids": []
  },
  {
    "evidence_id": "ev-00b93b21",
    "category": "procedure",
    "value": "Felley's Catheterisation (16F) on 28/2/26",
    "source_file": "patient 2 (1).pdf",
    "page_number": 15,
    "excerpt": "Yes 16F",
    "status": "verified",
    "confidence": 1.0,
    "readable": true,
    "identity_compatible": true,
    "conflict_ids": []
  },
  {
    "evidence_id": "ev-84ff03ab",
    "category": "procedure",
    "value": "Felley's Catheterisation R/C Rimar on 1/3/26",
    "source_file": "patient 2 (1).pdf",
    "page_number": 15,
    "excerpt": "R/C Rimar",
    "status": "verified",
    "confidence": 1.0,
    "readable": true,
    "identity_compatible": true,
    "conflict_ids": []
  },
  {
    "evidence_id": "ev-a1f6d222",
    "category": "procedure",
    "value": "Phototherapy on 27/2/2",
    "source_file": "patient 2 (1).pdf",
    "page_number": 15,
    "excerpt": "Yes",
    "status": "verified",
    "confidence": 1.0,
    "readable": true,
    "identity_compatible": true,
    "conflict_ids": []
  },
  {
    "evidence_id": "ev-edaa3760",
    "category": "procedure",
    "value": "Urine C./S. on 27/2/2",
    "source_file": "patient 2 (1).pdf",
    "page_number": 15,
    "excerpt": "Yes",
    "status": "verified",
    "confidence": 1.0,
    "readable": true,
    "identity_compatible": true,
    "conflict_ids": []
  },
  {
    "evidence_id": "ev-837d6021",
    "category": "procedure",
    "value": "Blood C./S. on 27/2/2",
    "source_file": "patient 2 (1).pdf",
    "page_number": 15,
    "excerpt": "Yes",
    "status": "verified",
    "confidence": 1.0,
    "readable": true,
    "identity_compatible": true,
    "conflict_ids": []
  },
  {
    "evidence_id": "ev-3868d122",
    "category": "procedure",
    "value": "PD Sets & Vein O Line (100ml) on 06/02/26",
    "source_file": "patient 2 (1).pdf",
    "page_number": 15,
    "excerpt": "Yes (100ml)",
    "status": "verified",
    "confidence": 1.0,
    "readable": true,
    "identity_compatible": true,
    "conflict_ids": []
  },
  {
    "evidence_id": "ev-fa5ffdda",
    "category": "procedure",
    "value": "PD Sets & Vein O Line on 27/2/2",
    "source_file": "patient 2 (1).pdf",
    "page_number": 15,
    "excerpt": "Yes",
    "status": "verified",
    "confidence": 1.0,
    "readable": true,
    "identity_compatible": true,
    "conflict_ids": []
  },
  {
    "evidence_id": "ev-1d71ead6",
    "category": "procedure",
    "value": "PD Sets & Vein O Line on 28/2/26",
    "source_file": "patient 2 (1).pdf",
    "page_number": 15,
    "excerpt": "Yes",
    "status": "verified",
    "confidence": 1.0,
    "readable": true,
    "identity_compatible": true,
    "conflict_ids": []
  },
  {
    "evidence_id": "ev-287064b1",
    "category": "procedure",
    "value": "PD Sets & Vein O Line on 1/3/26",
    "source_file": "patient 2 (1).pdf",
    "page_number": 15,
    "excerpt": "Yes",
    "status": "verified",
    "confidence": 1.0,
    "readable": true,
    "identity_compatible": true,
    "conflict_ids": []
  },
  {
    "evidence_id": "ev-f1789264",
    "category": "procedure",
    "value": "PD Sets & Vein O Line on 2/3/26",
    "source_file": "patient 2 (1).pdf",
    "page_number": 15,
    "excerpt": "Yes",
    "status": "verified",
    "confidence": 1.0,
    "readable": true,
    "identity_compatible": true,
    "conflict_ids": []
  },
  {
    "evidence_id": "ev-feb80a81",
    "category": "procedure",
    "value": "Oxygen on 06/02/26",
    "source_file": "patient 2 (1).pdf",
    "page_number": 15,
    "excerpt": "Yes",
    "status": "verified",
    "confidence": 1.0,
    "readable": true,
    "identity_compatible": true,
    "conflict_ids": []
  },
  {
    "evidence_id": "ev-279fc5b3",
    "category": "procedure",
    "value": "USG/ECHO on 27/2/2",
    "source_file": "patient 2 (1).pdf",
    "page_number": 15,
    "excerpt": "Yes",
    "status": "verified",
    "confidence": 1.0,
    "readable": true,
    "identity_compatible": true,
    "conflict_ids": []
  },
  {
    "evidence_id": "ev-f2ea2233",
    "category": "admission_date",
    "value": "26-2-26 6:14pm",
    "source_file": "patient 2 (1).pdf",
    "page_number": 16,
    "excerpt": "26-2-26 6:14pm",
    "status": "conflicting",
    "confidence": 1.0,
    "readable": true,
    "identity_compatible": true,
    "conflict_ids": [
      "conflict-b2decb5c"
    ]
  },
  {
    "evidence_id": "ev-c8f2e07e",
    "category": "clinical_context",
    "value": "General Consent Signed: Yes",
    "source_file": "patient 2 (1).pdf",
    "page_number": 16,
    "excerpt": "Yes",
    "status": "verified",
    "confidence": 1.0,
    "readable": true,
    "identity_compatible": true,
    "conflict_ids": []
  },
  {
    "evidence_id": "ev-dd490c06",
    "category": "clinical_context",
    "value": "Temperature: 98\u00b0F",
    "source_file": "patient 2 (1).pdf",
    "page_number": 16,
    "excerpt": "98\u00b0F",
    "status": "verified",
    "confidence": 1.0,
    "readable": true,
    "identity_compatible": true,
    "conflict_ids": []
  },
  {
    "evidence_id": "ev-71c2e21c",
    "category": "clinical_context",
    "value": "Pulse: 116 b/Min",
    "source_file": "patient 2 (1).pdf",
    "page_number": 16,
    "excerpt": "116 b /Min",
    "status": "verified",
    "confidence": 1.0,
    "readable": true,
    "identity_compatible": true,
    "conflict_ids": []
  },
  {
    "evidence_id": "ev-d1bbefa0",
    "category": "clinical_context",
    "value": "Respiration: 22 b/Min",
    "source_file": "patient 2 (1).pdf",
    "page_number": 16,
    "excerpt": "22 b /Min",
    "status": "verified",
    "confidence": 1.0,
    "readable": true,
    "identity_compatible": true,
    "conflict_ids": []
  },
  {
    "evidence_id": "ev-4b6c1577",
    "category": "clinical_context",
    "value": "Blood Pressure: 87/50",
    "source_file": "patient 2 (1).pdf",
    "page_number": 16,
    "excerpt": "87/50",
    "status": "verified",
    "confidence": 1.0,
    "readable": true,
    "identity_compatible": true,
    "conflict_ids": []
  },
  {
    "evidence_id": "ev-dfb36488",
    "category": "clinical_context",
    "value": "SPO2: 98",
    "source_file": "patient 2 (1).pdf",
    "page_number": 16,
    "excerpt": "98",
    "status": "verified",
    "confidence": 1.0,
    "readable": true,
    "identity_compatible": true,
    "conflict_ids": []
  },
  {
    "evidence_id": "ev-1371b377",
    "category": "clinical_context",
    "value": "GRBS: 443",
    "source_file": "patient 2 (1).pdf",
    "page_number": 16,
    "excerpt": "443",
    "status": "verified",
    "confidence": 1.0,
    "readable": true,
    "identity_compatible": true,
    "conflict_ids": []
  },
  {
    "evidence_id": "ev-7d17d07a",
    "category": "clinical_context",
    "value": "Weight: 71kg",
    "source_file": "patient 2 (1).pdf",
    "page_number": 16,
    "excerpt": "71kg",
    "status": "verified",
    "confidence": 1.0,
    "readable": true,
    "identity_compatible": true,
    "conflict_ids": []
  },
  {
    "evidence_id": "ev-37644647",
    "category": "clinical_context",
    "value": "Complaints during admission: Fever, General weakness since 3 days",
    "source_file": "patient 2 (1).pdf",
    "page_number": 16,
    "excerpt": "Fever, General weakness since 3 days",
    "status": "verified",
    "confidence": 1.0,
    "readable": true,
    "identity_compatible": true,
    "conflict_ids": []
  },
  {
    "evidence_id": "ev-1a963556",
    "category": "clinical_context",
    "value": "Oriented: Yes",
    "source_file": "patient 2 (1).pdf",
    "page_number": 16,
    "excerpt": "Yes",
    "status": "verified",
    "confidence": 1.0,
    "readable": true,
    "identity_compatible": true,
    "conflict_ids": []
  },
  {
    "evidence_id": "ev-ab9ae671",
    "category": "clinical_context",
    "value": "Level of Consciousness: Conscious",
    "source_file": "patient 2 (1).pdf",
    "page_number": 16,
    "excerpt": "Conscious",
    "status": "verified",
    "confidence": 1.0,
    "readable": true,
    "identity_compatible": true,
    "conflict_ids": []
  },
  {
    "evidence_id": "ev-611d862c",
    "category": "clinical_context",
    "value": "Speech: Clear",
    "source_file": "patient 2 (1).pdf",
    "page_number": 16,
    "excerpt": "Clear",
    "status": "verified",
    "confidence": 1.0,
    "readable": true,
    "identity_compatible": true,
    "conflict_ids": []
  },
  {
    "evidence_id": "ev-a2fadf51",
    "category": "clinical_context",
    "value": "Visual Impairment: None",
    "source_file": "patient 2 (1).pdf",
    "page_number": 16,
    "excerpt": "None",
    "status": "verified",
    "confidence": 1.0,
    "readable": true,
    "identity_compatible": true,
    "conflict_ids": []
  },
  {
    "evidence_id": "ev-63d7182f",
    "category": "clinical_context",
    "value": "Extremity Strength: Equal",
    "source_file": "patient 2 (1).pdf",
    "page_number": 16,
    "excerpt": "Equal",
    "status": "verified",
    "confidence": 1.0,
    "readable": true,
    "identity_compatible": true,
    "conflict_ids": []
  },
  {
    "evidence_id": "ev-1c48abf6",
    "category": "clinical_context",
    "value": "Pupils: Equal / Reactive",
    "source_file": "patient 2 (1).pdf",
    "page_number": 16,
    "excerpt": "Equal / Reactive",
    "status": "verified",
    "confidence": 1.0,
    "readable": true,
    "identity_compatible": true,
    "conflict_ids": []
  },
  {
    "evidence_id": "ev-fd0b5141",
    "category": "clinical_context",
    "value": "Hearing Impairment: None",
    "source_file": "patient 2 (1).pdf",
    "page_number": 16,
    "excerpt": "None",
    "status": "verified",
    "confidence": 1.0,
    "readable": true,
    "identity_compatible": true,
    "conflict_ids": []
  },
  {
    "evidence_id": "ev-038d2e7a",
    "category": "clinical_context",
    "value": "Pain: Yes",
    "source_file": "patient 2 (1).pdf",
    "page_number": 16,
    "excerpt": "Yes",
    "status": "verified",
    "confidence": 1.0,
    "readable": true,
    "identity_compatible": true,
    "conflict_ids": []
  },
  {
    "evidence_id": "ev-291fa1d8",
    "category": "clinical_context",
    "value": "Pain Location: Body",
    "source_file": "patient 2 (1).pdf",
    "page_number": 16,
    "excerpt": "Body",
    "status": "verified",
    "confidence": 1.0,
    "readable": true,
    "identity_compatible": true,
    "conflict_ids": []
  },
  {
    "evidence_id": "ev-05f305cb",
    "category": "clinical_context",
    "value": "Pain Scale: 6 Moderate Pain",
    "source_file": "patient 2 (1).pdf",
    "page_number": 16,
    "excerpt": "6 Moderate Pain",
    "status": "verified",
    "confidence": 1.0,
    "readable": true,
    "identity_compatible": true,
    "conflict_ids": []
  },
  {
    "evidence_id": "ev-c270ede0",
    "category": "clinical_context",
    "value": "Airway: Clear",
    "source_file": "patient 2 (1).pdf",
    "page_number": 16,
    "excerpt": "Clear",
    "status": "verified",
    "confidence": 1.0,
    "readable": true,
    "identity_compatible": true,
    "conflict_ids": []
  },
  {
    "evidence_id": "ev-28723b73",
    "category": "clinical_context",
    "value": "Dyspnea: Present",
    "source_file": "patient 2 (1).pdf",
    "page_number": 16,
    "excerpt": "Present",
    "status": "verified",
    "confidence": 1.0,
    "readable": true,
    "identity_compatible": true,
    "conflict_ids": []
  },
  {
    "evidence_id": "ev-1c2c97bf",
    "category": "clinical_context",
    "value": "Wheezing: No",
    "source_file": "patient 2 (1).pdf",
    "page_number": 16,
    "excerpt": "No",
    "status": "verified",
    "confidence": 1.0,
    "readable": true,
    "identity_compatible": true,
    "conflict_ids": []
  },
  {
    "evidence_id": "ev-39119b95",
    "category": "clinical_context",
    "value": "Cough: Yes",
    "source_file": "patient 2 (1).pdf",
    "page_number": 16,
    "excerpt": "Yes",
    "status": "verified",
    "confidence": 1.0,
    "readable": true,
    "identity_compatible": true,
    "conflict_ids": []
  },
  {
    "evidence_id": "ev-ea6d5659",
    "category": "clinical_context",
    "value": "Sputum: Yes",
    "source_file": "patient 2 (1).pdf",
    "page_number": 16,
    "excerpt": "Yes",
    "status": "verified",
    "confidence": 1.0,
    "readable": true,
    "identity_compatible": true,
    "conflict_ids": []
  },
  {
    "evidence_id": "ev-cd0c8976",
    "category": "clinical_context",
    "value": "Edema: Absent",
    "source_file": "patient 2 (1).pdf",
    "page_number": 16,
    "excerpt": "Absent",
    "status": "verified",
    "confidence": 1.0,
    "readable": true,
    "identity_compatible": true,
    "conflict_ids": []
  },
  {
    "evidence_id": "ev-7a14fb4c",
    "category": "clinical_context",
    "value": "Skin Perfusion: Warm",
    "source_file": "patient 2 (1).pdf",
    "page_number": 16,
    "excerpt": "Warm",
    "status": "verified",
    "confidence": 1.0,
    "readable": true,
    "identity_compatible": true,
    "conflict_ids": []
  },
  {
    "evidence_id": "ev-01cac1b2",
    "category": "clinical_context",
    "value": "Capillary refill: < 3 Secs",
    "source_file": "patient 2 (1).pdf",
    "page_number": 16,
    "excerpt": "< 3 Secs",
    "status": "verified",
    "confidence": 1.0,
    "readable": true,
    "identity_compatible": true,
    "conflict_ids": []
  },
  {
    "evidence_id": "ev-1db4d652",
    "category": "clinical_context",
    "value": "Skin Colour: Fresh",
    "source_file": "patient 2 (1).pdf",
    "page_number": 16,
    "excerpt": "Fresh",
    "status": "verified",
    "confidence": 1.0,
    "readable": true,
    "identity_compatible": true,
    "conflict_ids": []
  },
  {
    "evidence_id": "ev-e1d2514d",
    "category": "clinical_context",
    "value": "Skin Turgor: Good",
    "source_file": "patient 2 (1).pdf",
    "page_number": 16,
    "excerpt": "Good",
    "status": "verified",
    "confidence": 1.0,
    "readable": true,
    "identity_compatible": true,
    "conflict_ids": []
  },
  {
    "evidence_id": "ev-70b0a186",
    "category": "clinical_context",
    "value": "Mucous membrane: Intact",
    "source_file": "patient 2 (1).pdf",
    "page_number": 16,
    "excerpt": "Intact",
    "status": "verified",
    "confidence": 1.0,
    "readable": true,
    "identity_compatible": true,
    "conflict_ids": []
  },
  {
    "evidence_id": "ev-86f56135",
    "category": "clinical_context",
    "value": "Skin Condition: Pink / Moist",
    "source_file": "patient 2 (1).pdf",
    "page_number": 16,
    "excerpt": "Pink / Moist",
    "status": "verified",
    "confidence": 1.0,
    "readable": true,
    "identity_compatible": true,
    "conflict_ids": []
  },
  {
    "evidence_id": "ev-b4f3bd63",
    "category": "clinical_context",
    "value": "Skin Temperature: Warm",
    "source_file": "patient 2 (1).pdf",
    "page_number": 16,
    "excerpt": "Warm",
    "status": "verified",
    "confidence": 1.0,
    "readable": true,
    "identity_compatible": true,
    "conflict_ids": []
  },
  {
    "evidence_id": "ev-d9abb0b8",
    "category": "clinical_context",
    "value": "Skin Moisture: Moist",
    "source_file": "patient 2 (1).pdf",
    "page_number": 16,
    "excerpt": "Moist",
    "status": "verified",
    "confidence": 1.0,
    "readable": true,
    "identity_compatible": true,
    "conflict_ids": []
  },
  {
    "evidence_id": "ev-fbf989f9",
    "category": "clinical_context",
    "value": "Loss of Appetite: Yes",
    "source_file": "patient 2 (1).pdf",
    "page_number": 16,
    "excerpt": "Yes",
    "status": "verified",
    "confidence": 1.0,
    "readable": true,
    "identity_compatible": true,
    "conflict_ids": []
  },
  {
    "evidence_id": "ev-c1254452",
    "category": "clinical_context",
    "value": "Diarrhoea: Yes",
    "source_file": "patient 2 (1).pdf",
    "page_number": 16,
    "excerpt": "Diarrhoea",
    "status": "verified",
    "confidence": 1.0,
    "readable": true,
    "identity_compatible": true,
    "conflict_ids": []
  },
  {
    "evidence_id": "ev-293d31c3",
    "category": "clinical_context",
    "value": "Abdomen: Soft",
    "source_file": "patient 2 (1).pdf",
    "page_number": 16,
    "excerpt": "Soft",
    "status": "verified",
    "confidence": 1.0,
    "readable": true,
    "identity_compatible": true,
    "conflict_ids": []
  },
  {
    "evidence_id": "ev-dfcd9246",
    "category": "clinical_context",
    "value": "Swallowing difficulty: No",
    "source_file": "patient 2 (1).pdf",
    "page_number": 16,
    "excerpt": "No",
    "status": "verified",
    "confidence": 1.0,
    "readable": true,
    "identity_compatible": true,
    "conflict_ids": []
  },
  {
    "evidence_id": "ev-64f9b28b",
    "category": "clinical_context",
    "value": "Dysuria: Yes",
    "source_file": "patient 2 (1).pdf",
    "page_number": 16,
    "excerpt": "Yes",
    "status": "verified",
    "confidence": 1.0,
    "readable": true,
    "identity_compatible": true,
    "conflict_ids": []
  },
  {
    "evidence_id": "ev-967fdb80",
    "category": "clinical_context",
    "value": "Incontinence: No",
    "source_file": "patient 2 (1).pdf",
    "page_number": 16,
    "excerpt": "No",
    "status": "verified",
    "confidence": 1.0,
    "readable": true,
    "identity_compatible": true,
    "conflict_ids": []
  },
  {
    "evidence_id": "ev-fe190941",
    "category": "clinical_context",
    "value": "Hematuria: No",
    "source_file": "patient 2 (1).pdf",
    "page_number": 16,
    "excerpt": "No",
    "status": "verified",
    "confidence": 1.0,
    "readable": true,
    "identity_compatible": true,
    "conflict_ids": []
  },
  {
    "evidence_id": "ev-0351de4e",
    "category": "allergy",
    "value": "Drug Allergy: Not known",
    "source_file": "patient 2 (1).pdf",
    "page_number": 16,
    "excerpt": "NOT known",
    "status": "verified",
    "confidence": 1.0,
    "readable": true,
    "identity_compatible": true,
    "conflict_ids": []
  },
  {
    "evidence_id": "ev-8ce80ff4",
    "category": "allergy",
    "value": "Not known",
    "source_file": "patient 2 (1).pdf",
    "page_number": 17,
    "excerpt": "Known Drug Allergies - Not known",
    "status": "verified",
    "confidence": 1.0,
    "readable": true,
    "identity_compatible": true,
    "conflict_ids": []
  },
  {
    "evidence_id": "ev-400c659c",
    "category": "admission_date",
    "value": "06/01/26",
    "source_file": "patient 2 (1).pdf",
    "page_number": 17,
    "excerpt": "* Date Of Admission 06/01/26",
    "status": "conflicting",
    "confidence": 1.0,
    "readable": true,
    "identity_compatible": true,
    "conflict_ids": [
      "conflict-b2decb5c"
    ]
  },
  {
    "evidence_id": "ev-f4bef170",
    "category": "clinical_context",
    "value": "fever and general weakness",
    "source_file": "patient 2 (1).pdf",
    "page_number": 17,
    "excerpt": "patient complaints to fever and general weakness",
    "status": "verified",
    "confidence": 0.9,
    "readable": true,
    "identity_compatible": true,
    "conflict_ids": []
  },
  {
    "evidence_id": "ev-5deb6808",
    "category": "clinical_context",
    "value": "conscious and oriented",
    "source_file": "patient 2 (1).pdf",
    "page_number": 17,
    "excerpt": "patient councious and oriented",
    "status": "verified",
    "confidence": 0.9,
    "readable": true,
    "identity_compatible": true,
    "conflict_ids": []
  },
  {
    "evidence_id": "ev-2ae2fb5d",
    "category": "hospital_course",
    "value": "Vitals checked and recorded in ER chart",
    "source_file": "patient 2 (1).pdf",
    "page_number": 17,
    "excerpt": "patient checked the vital sign and recorded in ER chard.",
    "status": "verified",
    "confidence": 0.9,
    "readable": true,
    "identity_compatible": true,
    "conflict_ids": []
  },
  {
    "evidence_id": "ev-2a86ac7f",
    "category": "hospital_course",
    "value": "Patient seen by Doctor",
    "source_file": "patient 2 (1).pdf",
    "page_number": 17,
    "excerpt": "patient seen by Dsr.",
    "status": "verified",
    "confidence": 0.9,
    "readable": true,
    "identity_compatible": true,
    "conflict_ids": []
  },
  {
    "evidence_id": "ev-cd2119e6",
    "category": "procedure",
    "value": "IV cannulation done",
    "source_file": "patient 2 (1).pdf",
    "page_number": 17,
    "excerpt": "patient IV cannulation done to 9 (2) hand.",
    "status": "verified",
    "confidence": 0.8,
    "readable": true,
    "identity_compatible": true,
    "conflict_ids": []
  },
  {
    "evidence_id": "ev-42ebea14",
    "category": "hospital_course",
    "value": "Blood investigations sent to labs",
    "source_file": "patient 2 (1).pdf",
    "page_number": 17,
    "excerpt": "patient blood investigations send to labs collect all Reports",
    "status": "verified",
    "confidence": 0.9,
    "readable": true,
    "identity_compatible": true,
    "conflict_ids": []
  },
  {
    "evidence_id": "ev-9e705b6f",
    "category": "procedure",
    "value": "ECG done",
    "source_file": "patient 2 (1).pdf",
    "page_number": 17,
    "excerpt": "patient Ecg done.",
    "status": "verified",
    "confidence": 1.0,
    "readable": true,
    "identity_compatible": true,
    "conflict_ids": []
  },
  {
    "evidence_id": "ev-3d6dd02a",
    "category": "hospital_course",
    "value": "Case and blood reports informed to Dr. Shunya Sampal",
    "source_file": "patient 2 (1).pdf",
    "page_number": 17,
    "excerpt": "patient case and blood reports inform to Dsr. Shunya Sampal.",
    "status": "verified",
    "confidence": 0.9,
    "readable": true,
    "identity_compatible": true,
    "conflict_ids": []
  },
  {
    "evidence_id": "ev-48a44c2c",
    "category": "hospital_course",
    "value": "Admission to HDU",
    "source_file": "patient 2 (1).pdf",
    "page_number": 17,
    "excerpt": "patient Admission to HDU",
    "status": "verified",
    "confidence": 1.0,
    "readable": true,
    "identity_compatible": true,
    "conflict_ids": []
  },
  {
    "evidence_id": "ev-cc6526d2",
    "category": "hospital_course",
    "value": "Patient transferred to 3rd Floor",
    "source_file": "patient 2 (1).pdf",
    "page_number": 17,
    "excerpt": "patient Hand out to 3rd Floor",
    "status": "verified",
    "confidence": 0.9,
    "readable": true,
    "identity_compatible": true,
    "conflict_ids": []
  },
  {
    "evidence_id": "ev-3da65327",
    "category": "medication",
    "value": "IV medications",
    "source_file": "patient 2 (1).pdf",
    "page_number": 17,
    "excerpt": "patient IV medications given,",
    "status": "verified",
    "confidence": 1.0,
    "readable": true,
    "identity_compatible": true,
    "conflict_ids": []
  },
  {
    "evidence_id": "ev-17a58925",
    "category": "allergy",
    "value": "No known drug allergies",
    "source_file": "patient 2 (1).pdf",
    "page_number": 18,
    "excerpt": "not known",
    "status": "verified",
    "confidence": 0.9,
    "readable": true,
    "identity_compatible": true,
    "conflict_ids": []
  },
  {
    "evidence_id": "ev-0a517403",
    "category": "clinical_context",
    "value": "Date of observation: 28/12/26",
    "source_file": "patient 2 (1).pdf",
    "page_number": 18,
    "excerpt": "28/12/26",
    "status": "verified",
    "confidence": 0.9,
    "readable": true,
    "identity_compatible": true,
    "conflict_ids": []
  },
  {
    "evidence_id": "ev-6cee4b0b",
    "category": "hospital_course",
    "value": "Patient received to SDDU on 1st floor Gyno",
    "source_file": "patient 2 (1).pdf",
    "page_number": 18,
    "excerpt": "patient received to SDDU to 1st floor Gyno",
    "status": "verified",
    "confidence": 0.9,
    "readable": true,
    "identity_compatible": true,
    "conflict_ids": []
  },
  {
    "evidence_id": "ev-64e50da2",
    "category": "clinical_context",
    "value": "Patient is in 1st floor Gyno unit",
    "source_file": "patient 2 (1).pdf",
    "page_number": 18,
    "excerpt": "1st floor Gyno",
    "status": "verified",
    "confidence": 0.9,
    "readable": true,
    "identity_compatible": true,
    "conflict_ids": []
  },
  {
    "evidence_id": "ev-0da79af8",
    "category": "hospital_course",
    "value": "Patient said sounds done and observed conscious",
    "source_file": "patient 2 (1).pdf",
    "page_number": 18,
    "excerpt": "patient said sounds done & patient observed & conscious",
    "status": "verified",
    "confidence": 0.9,
    "readable": true,
    "identity_compatible": true,
    "conflict_ids": []
  },
  {
    "evidence_id": "ev-6e3b2262",
    "category": "hospital_course",
    "value": "Right upper cannula and operative band present",
    "source_file": "patient 2 (1).pdf",
    "page_number": 18,
    "excerpt": "Ru Cannula & op band present",
    "status": "verified",
    "confidence": 0.8,
    "readable": true,
    "identity_compatible": true,
    "conflict_ids": []
  },
  {
    "evidence_id": "ev-ab3c47c8",
    "category": "pending_result",
    "value": "PC results pending",
    "source_file": "patient 2 (1).pdf",
    "page_number": 18,
    "excerpt": "PC results",
    "status": "pending",
    "confidence": 0.9,
    "readable": true,
    "identity_compatible": true,
    "conflict_ids": []
  },
  {
    "evidence_id": "ev-54855cff",
    "category": "hospital_course",
    "value": "Capillary Blood Glucose (GRBS) monitored 8th hourly",
    "source_file": "patient 2 (1).pdf",
    "page_number": 18,
    "excerpt": "CLT GRBS 8th hourly",
    "status": "verified",
    "confidence": 0.85,
    "readable": true,
    "identity_compatible": true,
    "conflict_ids": []
  },
  {
    "evidence_id": "ev-69601c43",
    "category": "pending_result",
    "value": "CBC and serum creatinine results pending",
    "source_file": "patient 2 (1).pdf",
    "page_number": 18,
    "excerpt": "CBC ser. creet",
    "status": "pending",
    "confidence": 0.85,
    "readable": true,
    "identity_compatible": true,
    "conflict_ids": []
  },
  {
    "evidence_id": "ev-155bd247",
    "category": "hospital_course",
    "value": "Patient care handover given to night duty staff",
    "source_file": "patient 2 (1).pdf",
    "page_number": 18,
    "excerpt": "patient chary heard given to night duty staff",
    "status": "verified",
    "confidence": 0.8,
    "readable": true,
    "identity_compatible": true,
    "conflict_ids": []
  },
  {
    "evidence_id": "ev-f1ef4649",
    "category": "hospital_course",
    "value": "Patient care handover taken from Evening duty staff",
    "source_file": "patient 2 (1).pdf",
    "page_number": 18,
    "excerpt": "pat M chary heard taken from Evening duty staff",
    "status": "verified",
    "confidence": 0.8,
    "readable": true,
    "identity_compatible": true,
    "conflict_ids": []
  },
  {
    "evidence_id": "ev-04dc0d1f",
    "category": "hospital_course",
    "value": "Patient conscious and oriented",
    "source_file": "patient 2 (1).pdf",
    "page_number": 18,
    "excerpt": "patient conscious & oriented",
    "status": "verified",
    "confidence": 0.9,
    "readable": true,
    "identity_compatible": true,
    "conflict_ids": []
  },
  {
    "evidence_id": "ev-36442d83",
    "category": "hospital_course",
    "value": "Patient IV cannula and AD band present",
    "source_file": "patient 2 (1).pdf",
    "page_number": 18,
    "excerpt": "patient IV cannula & AD band present",
    "status": "verified",
    "confidence": 0.9,
    "readable": true,
    "identity_compatible": true,
    "conflict_ids": []
  },
  {
    "evidence_id": "ev-24c114b1",
    "category": "hospital_course",
    "value": "Patient vitals checked and recorded to monitor",
    "source_file": "patient 2 (1).pdf",
    "page_number": 18,
    "excerpt": "patient Vital checked & recorded to moni",
    "status": "verified",
    "confidence": 0.9,
    "readable": true,
    "identity_compatible": true,
    "conflict_ids": []
  }
]